thoth_pre_commit_hook/__init__.py
thoth_pre_commit_hook/thoth_advise.py
thoth_pre_commit_hook-0.1.3.dist-info/LICENSE
thoth_pre_commit_hook-0.1.3.dist-info/METADATA
thoth_pre_commit_hook-0.1.3.dist-info/WHEEL
thoth_pre_commit_hook-0.1.3.dist-info/entry_points.txt
thoth_pre_commit_hook-0.1.3.dist-info/top_level.txt
thoth_pre_commit_hook-0.1.3.dist-info/RECORD
