Metadata-Version: 2.1
Name: thoth-pre-commit-hook
Version: 0.1.3
Summary: Get Thoth recommendations in a pre-commit hook.
Home-page: https://github.com/thoth-station/thoth-pre-commit-hook
Author: Maya Costantini
Author-email: mcostant@redhat.com
License: GPLv3+
Project-URL: Source Code, https://github.com/thoth-station/thoth-pre-commit-hook/
Project-URL: Issues, https://github.com/thoth-station/thoth-pre-commit-hook/issues
Project-URL: Changelog, https://github.com/thoth-station/thoth-pre-commit-hook/blob/master/CHANGELOG.md
License-File: LICENSE
Requires-Dist: thamos
